{
    "issue_number": 69,
    "total_issue_number": 107,
    "bvid": "BV1RvtreME1b",
    "sub_chart_flag": true,
    "pk_flag": true,
    "main_chart": [
        {
            "aid": 113148161953544,
            "bvid": "BV1nqt4e6EVf",
            "title": "\u3010\u6d1b\u5929\u4f9d\u4e50\u6b63\u7eeb\u539f\u521b\u3011\u5e73\u751f\u4ed7\u5251\u4e0d\u8d1f\u537f\u3010\u5357\u5317\u7ec4\u3011\u3010\u83ab\u4e0e\u4eba\u8fa9\u3011\u3010\u6843\u82b1\u96eaProject\u3011",
            "pubdate": "2024-09-20 13:20:00",
            "author": "\u83ab\u4e0e\u4eba\u8fa9",
            "mid": 2478827,
            "pickup": "NO",
            "pic": "http://i2.hdslb.com/bfs/archive/d1c78f1f60d95bfc49daf63bb06ed19f7b9c5bdb.jpg",
            "pic_url": "/cover/69/av113148161953544.jpg",
            "url": "https://www.bilibili.com/video/BV1nqt4e6EVf",
            "score": 59599,
            "rank": 1,
            "view": 3799,
            "like": 966,
            "danmaku": 8,
            "reply": 88,
            "favorite": 797,
            "coin": 548,
            "share": 54
        },
        {
            "aid": 113146282908492,
            "bvid": "BV1S24deAEvt",
            "title": "\u5386\u65f6\u4e94\u5e74\u5927\u5408\u5531\u300a\u535a\u6b4c\u68a6\u6f9c\u300b\u300c\u5728\u6211\u4eec\u8eab\u540e\u662f\u6ee1\u5929\u661f\u5149\u300d\u3010\u6d1b\u5929\u4f9d\u8a00\u548c\u4e50\u6b63\u7eeb\u539f\u521b\u3011\u3010\u4f9d\u68a6\u00b7\u6d1b\u62fe_\u4f01\u52122.0\u6700\u7ec8\u7ae0/\u539f\u521b\u66f2PV\u4ed8\u3011",
            "pubdate": "2024-09-16 20:00:00",
            "author": "\u9752\u5929\u7ea4\u4e91-TsingClouds",
            "mid": 85722894,
            "pickup": "NO",
            "pic": "http://i2.hdslb.com/bfs/archive/e55178aeaed294d9d5435e3cf5e3d4ee6f5223fb.jpg",
            "pic_url": "/cover/69/av113146282908492.jpg",
            "url": "https://www.bilibili.com/video/BV1S24deAEvt",
            "score": 52660,
            "rank": 2,
            "view": 7090,
            "like": 1518,
            "danmaku": 334,
            "reply": 111,
            "favorite": 983,
            "coin": 453,
            "share": 57
        },
        {
            "aid": 113153648100402,
            "bvid": "BV1qEtveRE4V",
            "title": "\u3010Vsinger AI\u3011Attack\uff01\u3010ACE COVER\u3011\u3010\u6d1b\u5929\u4f9d \u8a00\u548c \u4e50\u6b63\u7eeb \u4e50\u6b63\u9f99\u7259 \u5fb5\u7fbd\u6469\u67ef \u58a8\u6e05\u5f26\u3011",
            "pubdate": "2024-09-17 23:41:56",
            "author": "\u767d\u7cd6\u306e\u6b63\u4e49\u94c3",
            "mid": 180668218,
            "pickup": "NO",
            "pic": "http://i0.hdslb.com/bfs/archive/87e380ebca96ef23f0b6d037925cc32867b5784d.jpg",
            "pic_url": "/cover/69/av113153648100402.jpg",
            "url": "https://www.bilibili.com/video/BV1qEtveRE4V",
            "score": 40527,
            "rank": 3,
            "view": 3706,
            "like": 1029,
            "danmaku": 6,
            "reply": 107,
            "favorite": 582,
            "coin": 463,
            "share": 61
        },
        {
            "aid": 113139370761683,
            "bvid": "BV11L42eYEyg",
            "title": "\u6211\u5df2\u5728\u766b\u72c2\u7684\u8fb9\u7f18\u2014\u2014\u300a\u8fb9\u7f18\u97f3\u566a\u300b\u4e50\u6b63\u7eeb \u539f\u521b",
            "pubdate": "2024-09-16 09:00:00",
            "author": "\u7ef5\u7ef5\u72fccottensheep",
            "mid": 499574378,
            "pickup": "NO",
            "pic": "http://i0.hdslb.com/bfs/archive/61f97fd5ed2f75b9cde5d257e838230107dd8fd1.jpg",
            "pic_url": "/cover/69/av113139370761683.jpg",
            "url": "https://www.bilibili.com/video/BV11L42eYEyg",
            "score": 39360,
            "rank": 4,
            "view": 5269,
            "like": 833,
            "danmaku": 6,
            "reply": 90,
            "favorite": 765,
            "coin": 243,
            "share": 33
        },
        {
            "aid": 113136787064375,
            "bvid": "BV1XztTeqEup",
            "title": "\u3010\u4e50\u6b63\u7eeb\u539f\u521b\u66f2/\u540e\u786c\u6838\u3011\u96e8\u8bed\u8a00/\u82e6\u6c34-p",
            "pubdate": "2024-09-15 11:30:00",
            "author": "\u82e6\u6c34-p",
            "mid": 219460749,
            "pickup": "NO",
            "pic": "http://i2.hdslb.com/bfs/archive/7c4d43067a90d330769216bf86a61eb0de99fa9a.jpg",
            "pic_url": "/cover/69/av113136787064375.jpg",
            "url": "https://www.bilibili.com/video/BV1XztTeqEup",
            "score": 36082,
            "rank": 5,
            "view": 2904,
            "like": 598,
            "danmaku": 7,
            "reply": 79,
            "favorite": 559,
            "coin": 240,
            "share": 50
        },
        {
            "aid": 113146551339485,
            "bvid": "BV1FH4denE6F",
            "title": "\u3010\u4e94\u8272\u6218\u961fAI\u3011Hear me\uff01\u3010ACE COVER\u3011\u3010\u6d1b\u5929\u4f9d/\u4e50\u6b63\u7eeb/\u5fb5\u7fbd\u6469\u67ef/\u58a8\u6e05\u5f26/\u4e50\u6b63\u9f99\u7259\u3011",
            "pubdate": "2024-09-16 17:40:22",
            "author": "\u767d\u7cd6\u306e\u6b63\u4e49\u94c3",
            "mid": 180668218,
            "pickup": "NO",
            "pic": "http://i0.hdslb.com/bfs/archive/d1b4cfc073f43e3b3976c82edcaec201f948f08e.jpg",
            "pic_url": "/cover/69/av113146551339485.jpg",
            "url": "https://www.bilibili.com/video/BV1FH4denE6F",
            "score": 31356,
            "rank": 6,
            "view": 12255,
            "like": 1401,
            "danmaku": 74,
            "reply": 135,
            "favorite": 675,
            "coin": 516,
            "share": 111
        },
        {
            "aid": 113147440598946,
            "bvid": "BV1dwtsedEVa",
            "title": "\u3010\u4e50\u6b63\u7eebV5\u3011\u4e00\u6837\u7684\u6708\u5149\u3010\u4e2d\u79cb\u8282\u5feb\u4e50\u55b5\u3011",
            "pubdate": "2024-09-17 00:00:00",
            "author": "Emakoto\u6c5f\u8bda\u309b",
            "mid": 3546373544740923,
            "pickup": "NO",
            "pic": "http://i0.hdslb.com/bfs/archive/3452f8472c5fbe4b8879c486f1eeae5bc449dd0e.jpg",
            "pic_url": "/cover/69/av113147440598946.jpg",
            "url": "https://www.bilibili.com/video/BV1dwtsedEVa",
            "score": 29512,
            "rank": 7,
            "view": 12730,
            "like": 107,
            "danmaku": 0,
            "reply": 17,
            "favorite": 949,
            "coin": 37,
            "share": 88
        },
        {
            "aid": 113131032418359,
            "bvid": "BV1wbtFewE5r",
            "title": "\u3010\u4e94\u8272\u6218\u961fAI\u3011\u7a7a\u6c14\u578b\u521b\u4f5c\u8005\u3010\u7406\u79d1\u751f\u5929\u4f9d\u9171\u3011\u3010\u6d1b\u5929\u4f9d/\u4e50\u6b63\u7eeb/\u4e50\u6b63\u9f99\u7259/\u58a8\u6e05\u5f26/\u5fb5\u7fbd\u6469\u67ef\u3011",
            "pubdate": "2024-09-14 19:00:00",
            "author": "\u7406\u79d1\u751f\u5929\u4f9d\u9171",
            "mid": 4662061,
            "pickup": "NO",
            "pic": "http://i0.hdslb.com/bfs/archive/0e89ffb32f5d66fd5d52a1d6fa60fa73703040be.jpg",
            "pic_url": "/cover/69/av113131032418359.jpg",
            "url": "https://www.bilibili.com/video/BV1wbtFewE5r",
            "score": 16492,
            "rank": 8,
            "view": 2142,
            "like": 519,
            "danmaku": 3,
            "reply": 50,
            "favorite": 304,
            "coin": 111,
            "share": 23
        },
        {
            "aid": 113074442864878,
            "bvid": "BV1eEHxeGENL",
            "title": "\u3010\u4e50\u6b63\u7eeb\u539f\u521b\u66f2\u3011\u4e07\u91cc\u9752\u5c71\uff0c\u7686\u5c3d\u4e88\u4f60\uff01\u3010V\u4f9d\u4f1a\u4e00\u5468\u5e74\u5355\u54c1\u3011",
            "pubdate": "2024-09-17 02:00:00",
            "author": "\u843d\u6ce0P",
            "mid": 3493104063613228,
            "pickup": "NO",
            "pic": "http://i1.hdslb.com/bfs/archive/a8ae6ee75d82086ab058e514906ca2488684f4ef.jpg",
            "pic_url": "/cover/69/av113074442864878.jpg",
            "url": "https://www.bilibili.com/video/BV1eEHxeGENL",
            "score": 9935,
            "rank": 9,
            "view": 1255,
            "like": 274,
            "danmaku": 0,
            "reply": 20,
            "favorite": 186,
            "coin": 57,
            "share": 12
        },
        {
            "aid": 113121519732296,
            "bvid": "BV1f547e6E9U",
            "title": "\u3010\u5c11\u5973\u524d\u7ebf\u540c\u4eba\u66f2\u3011\u8774\u8776\u7684\u65f6\u95f4\u3010\u9732\u5c3c\u897f\u4e9a\u89d2\u8272\u66f2\u3011",
            "pubdate": "2024-09-14 20:00:00",
            "author": "GRF-YING",
            "mid": 482858325,
            "pickup": "NO",
            "pic": "http://i2.hdslb.com/bfs/archive/6bd41172cc772428814cc6a41440b59487dcf61b.jpg",
            "pic_url": "/cover/69/av113121519732296.jpg",
            "url": "https://www.bilibili.com/video/BV1f547e6E9U",
            "score": 8812,
            "rank": 10,
            "view": 2863,
            "like": 329,
            "danmaku": 2,
            "reply": 28,
            "favorite": 182,
            "coin": 154,
            "share": 12
        },
        {
            "aid": 113147155384604,
            "bvid": "BV1CbtseME3e",
            "title": "\u3010\u6d1b\u5929\u4f9d|\u4e50\u6b63\u7eeb\u3011\u300a\u5343\u91cc\u9080\u6708\u300b\u201c\u4e2d\u79cb\u8282\u5feb\u4e50\uff01\uff01\u201d",
            "pubdate": "2024-09-17 00:00:00",
            "author": "\u5b87\u8861Yu_H",
            "mid": 94898001,
            "pickup": "NO",
            "pic": "http://i1.hdslb.com/bfs/archive/5a01b268cb2e16fe9e88337609dfadd6605da77b.jpg",
            "pic_url": "/cover/69/av113147155384604.jpg",
            "url": "https://www.bilibili.com/video/BV1CbtseME3e",
            "score": 8434,
            "rank": 11,
            "view": 2055,
            "like": 379,
            "danmaku": 1,
            "reply": 42,
            "favorite": 168,
            "coin": 110,
            "share": 14
        },
        {
            "aid": 113148430457711,
            "bvid": "BV19Gt4eoECM",
            "title": "\u3010Vsinger AI\u3011\u65f7\u53e4\u56de\u54cd\u3010\u5fd8\u5ddd\u98ce\u534e\u5f55\u3011\u3010ACE Studio Cover\u3011",
            "pubdate": "2024-09-17 12:00:00",
            "author": "\u4f0a\u8299\u7433_Eve",
            "mid": 1845235988,
            "pickup": "NO",
            "pic": "http://i0.hdslb.com/bfs/archive/2af939a727be191146ea620331e3e1d64783e039.jpg",
            "pic_url": "/cover/69/av113148430457711.jpg",
            "url": "https://www.bilibili.com/video/BV19Gt4eoECM",
            "score": 7955,
            "rank": 12,
            "view": 1688,
            "like": 266,
            "danmaku": 13,
            "reply": 52,
            "favorite": 156,
            "coin": 112,
            "share": 19
        },
        {
            "aid": 113152524027291,
            "bvid": "BV1xztYeYEuE",
            "title": "\u201c\u82e5\u6211\u4e0d\u503c\u5f97\u4f60\u8de8\u8d8a\u661f\u6cb3\u4e4b\u9065  \u53ea\u613f\u4f60\u5728\u6b64\u591c\u62ac\u773c\u770b\u8fd9\u9e4a\u6865\u201d\u2014\u2014\u300a\u9e4a\u6865\u300b\u3010\u6d1b\u5929\u4f9d/\u4e50\u6b63\u7eeb\u3011\u3010\u539f\u521bPV\u4ed8\u3011",
            "pubdate": "2024-09-17 21:00:00",
            "author": "\u5e74\u7cd5_Rue",
            "mid": 43914949,
            "pickup": "NO",
            "pic": "http://i2.hdslb.com/bfs/archive/262f98139d9a828185e660d75b9b53e3d6afb2fe.jpg",
            "pic_url": "/cover/69/av113152524027291.jpg",
            "url": "https://www.bilibili.com/video/BV1xztYeYEuE",
            "score": 7721,
            "rank": 13,
            "view": 1704,
            "like": 257,
            "danmaku": 0,
            "reply": 33,
            "favorite": 170,
            "coin": 58,
            "share": 6
        },
        {
            "aid": 113111302410011,
            "bvid": "BV17zpxeQEsb",
            "title": "\u3010\u4e50\u6b63\u7eebAI\u539f\u521b\u3011\u5b57\u95f4\u7e41\u661f\u6765\u2014\u2014\u201c\u90a3\u6bb5\u6666\u6697\u7684\u5c81\u6708\u91cc\uff0c\u9ed1\u767d\u5b57\u95f4\u7684\u7e41\u661f\u7167\u4eae\u6211\u4eec\u524d\u884c\u3002\u201d \u4e13\u8f91\u300c\u9752\u6625\u00b701\u300d[\u539f\u521bPV\u4ed8]",
            "pubdate": "2024-09-10 14:30:00",
            "author": "\u8340\u90aaoffo",
            "mid": 7727120,
            "pickup": "NO",
            "pic": "http://i2.hdslb.com/bfs/archive/94d5760bfb9eb999324ad15c03826a35414d8d9a.jpg",
            "pic_url": "/cover/69/av113111302410011.jpg",
            "url": "https://www.bilibili.com/video/BV17zpxeQEsb",
            "score": 6819,
            "rank": 14,
            "view": 5367,
            "like": 585,
            "danmaku": 3,
            "reply": 24,
            "favorite": 165,
            "coin": 62,
            "share": 35
        },
        {
            "aid": 113140981505187,
            "bvid": "BV1wN4mecE6v",
            "title": "\u3010\u4e50\u6b63\u7eebAI\u3011\u7ea2\uff08 ACE Studio Cover \uff09",
            "pubdate": "2024-09-15 18:07:05",
            "author": "\u738b\u724cp",
            "mid": 5343158,
            "pickup": "NO",
            "pic": "http://i0.hdslb.com/bfs/archive/1b64bf2c463188e548925783cfc766064e191543.jpg",
            "pic_url": "/cover/69/av113140981505187.jpg",
            "url": "https://www.bilibili.com/video/BV1wN4mecE6v",
            "score": 5069,
            "rank": 15,
            "view": 1453,
            "like": 168,
            "danmaku": 2,
            "reply": 18,
            "favorite": 116,
            "coin": 57,
            "share": 8
        },
        {
            "aid": 113140494769081,
            "bvid": "BV1BR4meREAr",
            "title": "\u3010\u4e50\u6b63\u9f99\u7259\u00d7\u4e50\u6b63\u7eeb\u3011\u90a3\u65f6\u767d\u4e91\u60a0\u60a0\uff0c\u98d8\u5728\u6211\u4eec\u513f\u65f6\u7684\u56de\u5fc6\u3002\u3010ACE Studio Cover\u3011\uff08Cover\uff1a\u738b\u5b87\u5b99Leto\u3001\u5e84\u6dc7\u739f29\uff09",
            "pubdate": "2024-09-15 15:59:25",
            "author": "\u66ae\u8272\u672a\u91cf",
            "mid": 272904686,
            "pickup": "NO",
            "pic": "http://i0.hdslb.com/bfs/archive/8dd6777fd058512a76685ef0775e4548b9406d5d.jpg",
            "pic_url": "/cover/69/av113140494769081.jpg",
            "url": "https://www.bilibili.com/video/BV1BR4meREAr",
            "score": 3700,
            "rank": 16,
            "view": 689,
            "like": 98,
            "danmaku": 3,
            "reply": 29,
            "favorite": 73,
            "coin": 46,
            "share": 10
        },
        {
            "aid": 113130143223374,
            "bvid": "BV1dY4ZeSEkX",
            "title": "\u3010\u4e50\u6b63\u7eebACE\u3011\u300a\u6211\u591a\u60f3\u8bf4\u518d\u89c1\u554a\u300b\u2014\u2014\u201c\u6211\u4e5f\u60f3\u8bf4\u518d\u89c1\u554a\uff0c\u98ce\u6708\u68a6\u8bdd \u628a\u60f3\u4e0e\u5ff5\u7559\u4e0b\u3002\u201d",
            "pubdate": "2024-09-13 22:30:00",
            "author": "FateRo",
            "mid": 44984626,
            "pickup": "NO",
            "pic": "http://i0.hdslb.com/bfs/archive/cf8e7247206e5817977790c57def5f02f18618a7.jpg",
            "pic_url": "/cover/69/av113130143223374.jpg",
            "url": "https://www.bilibili.com/video/BV1dY4ZeSEkX",
            "score": 3564,
            "rank": 17,
            "view": 798,
            "like": 132,
            "danmaku": 1,
            "reply": 21,
            "favorite": 76,
            "coin": 32,
            "share": 4
        },
        {
            "aid": 113156064020126,
            "bvid": "BV1RFt3eSEay",
            "title": "\u3010\u4e50\u6b63\u7eebAI\u3011\u53c8\u89c1\u00b7\u660e\u6708\u5149 [2024\u4e2d\u79cb\u6f2b\u6e38\u591c.ver]",
            "pubdate": "2024-09-19 18:00:00",
            "author": "\u7dbe\u57ceAyashiro",
            "mid": 1360362313,
            "pickup": "NO",
            "pic": "http://i0.hdslb.com/bfs/archive/3536234c5a220ea4f37b882bb23a9ac53c83491a.jpg",
            "pic_url": "/cover/69/av113156064020126.jpg",
            "url": "https://www.bilibili.com/video/BV1RFt3eSEay",
            "score": 3402,
            "rank": 18,
            "view": 515,
            "like": 84,
            "danmaku": 0,
            "reply": 12,
            "favorite": 70,
            "coin": 15,
            "share": 4
        },
        {
            "aid": 113142675800758,
            "bvid": "BV1Kw4QemE1V",
            "title": "\u3010\u5357\u5317\u7ec4\u3011\u4e2d\u79cb\u00b7\u5f52\u4e61\u68a6\u3010\u6d1b\u5929\u4f9d\u3011\u3010\u4e50\u6b63\u7eeb\u3011\u3010\u6ca8\u6f2a\u3011\u3010\u67f3\u4f9d\u4f9d\u3011\u3010swiss126\u3011",
            "pubdate": "2024-09-17 12:00:00",
            "author": "swiss126",
            "mid": 7493323,
            "pickup": "NO",
            "pic": "http://i0.hdslb.com/bfs/archive/c0e5e113998a995ac14f7e4dc9f8b9de6c1a16c1.jpg",
            "pic_url": "/cover/69/av113142675800758.jpg",
            "url": "https://www.bilibili.com/video/BV1Kw4QemE1V",
            "score": 3111,
            "rank": 19,
            "view": 750,
            "like": 274,
            "danmaku": 8,
            "reply": 27,
            "favorite": 51,
            "coin": 30,
            "share": 26
        },
        {
            "aid": 113114053873180,
            "bvid": "BV1SF4YeKERH",
            "title": "19\u4f4d\u865a\u62df\u6b4c\u59ec\u5408\u5531\u300a\u8d77\u98ce\u4e86\u300b\u2014\u2014\u201c\u5fc3\u4e4b\u6240\u52a8\uff0c\u4e14\u5c31\u968f\u7f18\u53bb\u5427\u201d\u3010\u5de8\u9f99\u5408\u8c03\u7ec4 HB To \u9b3c\u9762P\u3011",
            "pubdate": "2024-09-11 10:00:00",
            "author": "\u96e8\u5df7\u72ec\u914cRainfall",
            "mid": 341906317,
            "pickup": "NO",
            "pic": "http://i0.hdslb.com/bfs/archive/afa0c54cc9c37b086d6b184ef5c51aece139e0b8.jpg",
            "pic_url": "/cover/69/av113114053873180.jpg",
            "url": "https://www.bilibili.com/video/BV1SF4YeKERH",
            "score": 2989,
            "rank": 20,
            "view": 1079,
            "like": 117,
            "danmaku": 1,
            "reply": 5,
            "favorite": 74,
            "coin": 31,
            "share": 22
        }
    ],
    "sub_chart": [
        {
            "aid": 113106000871735,
            "bvid": "BV14mp7e5EXK",
            "title": "\u3010\u4e50\u6b63\u7eeb\u3011\u300a\u4e07\u6709\u5f15\u529b\u300b\u2014\u2014\u201c\u6211\u4eec\u7684\u7231\u60c5\uff0c\u662f\u547d\u4e2d\u6ce8\u5b9a\u201d\u3010HB To \u9b3c\u9762P\u3011",
            "pubdate": "2024-09-11 12:00:00",
            "author": "\u96e8\u5df7\u72ec\u914cRainfall",
            "mid": 341906317,
            "pickup": "NO",
            "pic": "http://i2.hdslb.com/bfs/archive/ec037e10b76491d98bda62f656d8b3508b7a2c6a.jpg",
            "pic_url": "/cover/69/av113106000871735.jpg",
            "url": "https://www.bilibili.com/video/BV14mp7e5EXK",
            "score": 2832,
            "rank": 21,
            "view": 1107,
            "like": 129,
            "danmaku": 0,
            "reply": 1,
            "favorite": 73,
            "coin": 28,
            "share": 8
        },
        {
            "aid": 113164687575973,
            "bvid": "BV17TtQeMEfF",
            "title": "\u3010\u4e50\u6b63\u7eebAI\u539f\u521b\u3011\u590f\u4e0e\u6d6a\u82b1\u66f2\u2016\u201c\u66fe\u7ecf\u7f8e\u4e3d\u800c\u9a84\u50b2\u7740\u7684\u5374\u6401\u6d45\u4ef0\u8eba\u201d\u3010\u5c71\u6d77\u65e7\u4e8b\u00b703\u3011",
            "pubdate": "2024-09-19 22:31:19",
            "author": "\u8336\u989c\u4f59\u96ea",
            "mid": 521848014,
            "pickup": "NO",
            "pic": "http://i1.hdslb.com/bfs/archive/ea12511d317eeb6e8270d6596bf05090a1b5cc73.jpg",
            "pic_url": "/cover/69/av113164687575973.jpg",
            "url": "https://www.bilibili.com/video/BV17TtQeMEfF",
            "score": 2501,
            "rank": 22,
            "view": 234,
            "like": 64,
            "danmaku": 0,
            "reply": 19,
            "favorite": 42,
            "coin": 8,
            "share": 4
        },
        {
            "aid": 113148111620059,
            "bvid": "BV1Ekt4eTEqr",
            "title": "\u3010\u5fb5\u7fbd\u6469\u67efAI\ud83c\udf4eVsinger\u5168\u5458\u3011\u8f6c\u751f\u6797\u6a8e\u3010COVER\u3011\u770b\u7b80\u4ecb",
            "pubdate": "2024-09-17 17:00:00",
            "author": "TRANSTORM\u5e7b\u5316\u98ce",
            "mid": 4851040,
            "pickup": "NO",
            "pic": "http://i1.hdslb.com/bfs/archive/c4644e82fdd18b543a09ef5ef22b80523fb36194.jpg",
            "pic_url": "/cover/69/av113148111620059.jpg",
            "url": "https://www.bilibili.com/video/BV1Ekt4eTEqr",
            "score": 2354,
            "rank": 23,
            "view": 942,
            "like": 128,
            "danmaku": 6,
            "reply": 9,
            "favorite": 71,
            "coin": 22,
            "share": 8
        },
        {
            "aid": 113152658311199,
            "bvid": "BV1zQtYesEYG",
            "title": "[\u8a00\u548cAI/\u4e50\u6b63\u7eebV3] \u706f\u706b\u91cc\u7684\u4e2d\u56fd [\u4e2d\u79cb\u5feb\u4e50][\u98de\u9e1f/\u4f9d\u72d0]",
            "pubdate": "2024-09-17 21:30:00",
            "author": "\u98de\u9e1f\u5495\u5495\u53eb",
            "mid": 319244624,
            "pickup": "NO",
            "pic": "http://i2.hdslb.com/bfs/archive/7791c7698712ac07ea64157b0aeca55d346d7aed.jpg",
            "pic_url": "/cover/69/av113152658311199.jpg",
            "url": "https://www.bilibili.com/video/BV1zQtYesEYG",
            "score": 2135,
            "rank": 24,
            "view": 385,
            "like": 67,
            "danmaku": 1,
            "reply": 10,
            "favorite": 44,
            "coin": 17,
            "share": 3
        },
        {
            "aid": 113144504518750,
            "bvid": "BV1V94RezEYe",
            "title": "\u3010\u4e2d\u79cb\u5408\u5531\u3011\u300a\u6708\u795e\u8d4b\u300b\u3010\u6d1b\u5929\u4f9d/\u8a00\u548c/\u4e50\u6b63\u7eeb/\u590f\u8bed\u9065/\u4e1c\u65b9\u6800\u5b50AI\u3011",
            "pubdate": "2024-09-17 00:00:00",
            "author": "\u6d1b\u65e0\u5c18P",
            "mid": 3546707572820023,
            "pickup": "NO",
            "pic": "http://i2.hdslb.com/bfs/archive/3d9b9737c36f9bd6260009a4404384bbe344431a.jpg",
            "pic_url": "/cover/69/av113144504518750.jpg",
            "url": "https://www.bilibili.com/video/BV1V94RezEYe",
            "score": 1973,
            "rank": 25,
            "view": 567,
            "like": 111,
            "danmaku": 2,
            "reply": 13,
            "favorite": 46,
            "coin": 12,
            "share": 0
        },
        {
            "aid": 113142239596540,
            "bvid": "BV1Ko4UeVEm3",
            "title": "\u201c\u4f46\u613f\u4eba\u95f4\u5343\u91cc\u300a\u5171\u5a75\u5a1f\u300b\u201d\u3010\u6d1b\u5929\u4f9d\u3001\u4e50\u6b63\u7eeb\u4e2d\u79cb\u539f\u521b\uff08\u5357\u5317\u7ec4\uff09\u3011",
            "pubdate": "2024-09-17 00:00:00",
            "author": "\u6d1b\u5929\u4f9dP",
            "mid": 592947813,
            "pickup": "NO",
            "pic": "http://i2.hdslb.com/bfs/archive/48002642afdddf4c09397778849a42270cf921cf.jpg",
            "pic_url": "/cover/69/av113142239596540.jpg",
            "url": "https://www.bilibili.com/video/BV1Ko4UeVEm3",
            "score": 1853,
            "rank": 26,
            "view": 930,
            "like": 107,
            "danmaku": 19,
            "reply": 35,
            "favorite": 47,
            "coin": 6,
            "share": 9
        },
        {
            "aid": 113142105381653,
            "bvid": "BV15y4UeHEKv",
            "title": "\u3010\u4e50\u6b63\u7eeb\u3011\u300a\u65f6\u5019\u300b\u2014\u2014\u770b\u4f3c\u7b80\u5355\uff0c\u6012\u706b\u5219\u7a7f\u5589\uff08\u8c01\u8bf4ACE\u7eeb\u4e0a\u4e0d\u53bb\u516d\u7ec4\uff1f\uff09\uff08ACE cover\u5218\u7f8e\u9e9f\uff09",
            "pubdate": "2024-09-15 22:45:58",
            "author": "\u7a7a\u8be9_",
            "mid": 514721889,
            "pickup": "NO",
            "pic": "http://i2.hdslb.com/bfs/archive/f90097b2a0eac6561a05d889f31c34ff040ae3a6.jpg",
            "pic_url": "/cover/69/av113142105381653.jpg",
            "url": "https://www.bilibili.com/video/BV15y4UeHEKv",
            "score": 1745,
            "rank": 27,
            "view": 1561,
            "like": 71,
            "danmaku": 0,
            "reply": 8,
            "favorite": 47,
            "coin": 8,
            "share": 1
        },
        {
            "aid": 113158211635553,
            "bvid": "BV1Fjt5eqEVr",
            "title": "\u3010\u4e50\u6b63\u7eeb\u7ffb\u5531\u3011\u661f\u6d77\u6f2b\u6e38 \u8ddf\u7eeb\u7eeb\u4e00\u8d77\u73a9\u8d5b\u5c14\u53f7\uff01\uff01",
            "pubdate": "2024-09-18 21:05:00",
            "author": "\u6d1b\u96e8\u8fb0P",
            "mid": 402274020,
            "pickup": "PK",
            "pic": "http://i2.hdslb.com/bfs/archive/df6187d3acbb4e3de91b3a9ecbca465fead00b52.jpg",
            "pic_url": "/cover/69/av113158211635553.jpg",
            "url": "https://www.bilibili.com/video/BV1Fjt5eqEVr",
            "score": 1628,
            "rank": 28,
            "view": 451,
            "like": 80,
            "danmaku": 0,
            "reply": 15,
            "favorite": 34,
            "coin": 15,
            "share": 3
        },
        {
            "aid": 113133649664736,
            "bvid": "BV1mwtAejEho",
            "title": "\u3010\u5357\u5317\u6781\u661f\u3011\u706f\u706b\u3010Vocaloid Cover\u3011",
            "pubdate": "2024-09-14 10:58:59",
            "author": "\u549a\u549a\u549a\u545b\u549a\u545b",
            "mid": 38294579,
            "pickup": "NO",
            "pic": "http://i0.hdslb.com/bfs/archive/e38a824d03def02b15225adc53abeeab7f5623b6.jpg",
            "pic_url": "/cover/69/av113133649664736.jpg",
            "url": "https://www.bilibili.com/video/BV1mwtAejEho",
            "score": 1473,
            "rank": 29,
            "view": 375,
            "like": 43,
            "danmaku": 0,
            "reply": 8,
            "favorite": 35,
            "coin": 10,
            "share": 3
        },
        {
            "aid": 113134891244449,
            "bvid": "BV1TgtTetE15",
            "title": "\u3010\u6d1b\u5929\u4f9d&\u4e50\u6b63\u7eeb\u3011\u666e\u901a\u7684\u8c03\u4f11\uff08\u666e\u901aDISCO\uff09",
            "pubdate": "2024-09-15 00:00:00",
            "author": "\u5317\u51a5\u9cb6\u9c7c\u738b",
            "mid": 241061856,
            "pickup": "NO",
            "pic": "http://i1.hdslb.com/bfs/archive/b228db4ad0ac61d208e5c313d68e150e20e82698.jpg",
            "pic_url": "/cover/69/av113134891244449.jpg",
            "url": "https://www.bilibili.com/video/BV1TgtTetE15",
            "score": 1144,
            "rank": 30,
            "view": 652,
            "like": 152,
            "danmaku": 0,
            "reply": 12,
            "favorite": 19,
            "coin": 12,
            "share": 13
        },
        {
            "aid": 113135763588366,
            "bvid": "BV1VLtKeNEN6",
            "title": "\u3010\u6d1b\u5929\u4f9dAI\u00d7\u4e50\u6b63\u7eebAI\u3011\u52fe\u6307\u8d77\u8a93\u3010\u5357\u5317\u7ec4\u7ffb\u5531\u3011",
            "pubdate": "2024-09-14 19:53:06",
            "author": "\u4e16\u754c\u7b2c\u4f9d\u7684\u83ab\u4e03\u6bbf\u4e0b",
            "mid": 171633221,
            "pickup": "NO",
            "pic": "http://i2.hdslb.com/bfs/archive/e6bc1ce5346aa1459b118fbcde632cdf51197185.jpg",
            "pic_url": "/cover/69/av113135763588366.jpg",
            "url": "https://www.bilibili.com/video/BV1VLtKeNEN6",
            "score": 1065,
            "rank": 31,
            "view": 529,
            "like": 79,
            "danmaku": 0,
            "reply": 12,
            "favorite": 24,
            "coin": 6,
            "share": 4
        },
        {
            "aid": 113170274393833,
            "bvid": "BV1XJbAeZE8q",
            "title": "\u3010\u6d1b\u5929\u4f9dAI/\u4e50\u6b63\u7eebAI\u3011\u4e0d\u8d1f\u97f6\u5149",
            "pubdate": "2024-09-20 22:13:16",
            "author": "\u4e50\u6b63\u6ca1\u6709\u7eeb",
            "mid": 6057473,
            "pickup": "NO",
            "pic": "http://i1.hdslb.com/bfs/archive/ead09c62b26312d92750417d53ccb78e631a2826.jpg",
            "pic_url": "/cover/69/av113170274393833.jpg",
            "url": "https://www.bilibili.com/video/BV1XJbAeZE8q",
            "score": 1035,
            "rank": 32,
            "view": 128,
            "like": 27,
            "danmaku": 0,
            "reply": 3,
            "favorite": 19,
            "coin": 7,
            "share": 0
        },
        {
            "aid": 113141736278096,
            "bvid": "BV1mi4Se1EV7",
            "title": "\u3010\u4e50\u6b63\u7eeb\u3011\u6625\u5ead\u96ea",
            "pubdate": "2024-09-15 21:13:06",
            "author": "\u96fb\u6666\u51a5",
            "mid": 337805546,
            "pickup": "NO",
            "pic": "http://i0.hdslb.com/bfs/archive/247343adb8a14d1376aacac64811617f21b136a5.jpg",
            "pic_url": "/cover/69/av113141736278096.jpg",
            "url": "https://www.bilibili.com/video/BV1mi4Se1EV7",
            "score": 1003,
            "rank": 33,
            "view": 628,
            "like": 43,
            "danmaku": 0,
            "reply": 5,
            "favorite": 24,
            "coin": 8,
            "share": 0
        },
        {
            "aid": 113153564351940,
            "bvid": "BV1wQtvePEoe",
            "title": "\u3010HB to \u7389\u7c73\u3011\u201c\u603b\u4ee5\u4e3a \u5e74\u5c11\u7684\u7231\u4f1a\u6c38\u8fdc\u201d\u3010\u4e50\u6b63\u7eebACE\u3011\u82ad\u8549\u591c\u96e8 \u3010ACE cover\u3011",
            "pubdate": "2024-09-17 23:23:03",
            "author": "\u6d1b\u53f6p",
            "mid": 381865582,
            "pickup": "NO",
            "pic": "http://i0.hdslb.com/bfs/archive/3bf7dff135bc0c5b7038807f2afea26bcb3e2e1c.jpg",
            "pic_url": "/cover/69/av113153564351940.jpg",
            "url": "https://www.bilibili.com/video/BV1wQtvePEoe",
            "score": 970,
            "rank": 34,
            "view": 171,
            "like": 25,
            "danmaku": 6,
            "reply": 12,
            "favorite": 11,
            "coin": 24,
            "share": 5
        },
        {
            "aid": 113152943594988,
            "bvid": "BV1VxtYeVE3V",
            "title": "\u3010\u6d1b\u5929\u4f9d\u4e50\u6b63\u7eebv5\u3011\u53e4\u65e7\u4eba\u95f4\u2014\u2014\u201c\u4ee5\u8bcd\u8bdd\u4e3a\u773c\uff0c\u63a2\u7d22\u53e4\u65e7\u4eba\u95f4\u201d\u3010\u521d\u96ea\u5e8f\u3011",
            "pubdate": "2024-09-17 20:46:35",
            "author": "\u521d\u96ea\u5e8f_",
            "mid": 3493142296791663,
            "pickup": "NO",
            "pic": "http://i1.hdslb.com/bfs/archive/c60a64cbcedc010c4bb609fd7dfcb82f41de8ce8.jpg",
            "pic_url": "/cover/69/av113152943594988.jpg",
            "url": "https://www.bilibili.com/video/BV1VxtYeVE3V",
            "score": 773,
            "rank": 35,
            "view": 174,
            "like": 29,
            "danmaku": 0,
            "reply": 7,
            "favorite": 19,
            "coin": 1,
            "share": 0
        },
        {
            "aid": 113152909905712,
            "bvid": "BV1zgtYepEWV",
            "title": "\u3010Vsinger\u5168\u5458\u3011\u7fa4\u9752\u8d5e\u6b4c(\u7fa4\u9752\u8b9a\u6b4c)\u4e2d\u6587\u7248(Ace cover)(Project Sekai\u4e16\u754c\u8ba1\u5212\u4e00\u5468\u5e74\u7eaa\u5ff5\u66f2)",
            "pubdate": "2024-09-17 20:36:09",
            "author": "\u6749\u6749Mu",
            "mid": 3461568461278017,
            "pickup": "NO",
            "pic": "http://i0.hdslb.com/bfs/archive/0466fb32b55608b3f37ffd153b07f22aeaec7fe1.jpg",
            "pic_url": "/cover/69/av113152909905712.jpg",
            "url": "https://www.bilibili.com/video/BV1zgtYepEWV",
            "score": 742,
            "rank": 36,
            "view": 1875,
            "like": 72,
            "danmaku": 0,
            "reply": 4,
            "favorite": 22,
            "coin": 7,
            "share": 2
        },
        {
            "aid": 113170509205624,
            "bvid": "BV12XbwejEye",
            "title": "\u3010\u6cd5\u624e/\u4e50\u6b63\u7eebAI\u6cd5\u8bed\u7ffb\u5531\u3011\u6740\u4eba\u4ea4\u54cd\u66f2 L'assasymphonie",
            "pubdate": "2024-09-20 23:11:53",
            "author": "\u4e0d\u5c0a-\u60af\u661f\u8c23",
            "mid": 32357957,
            "pickup": "NO",
            "pic": "http://i0.hdslb.com/bfs/archive/914f26ee5495a09626a74fa0d48e7bb5a778b999.jpg",
            "pic_url": "/cover/69/av113170509205624.jpg",
            "url": "https://www.bilibili.com/video/BV12XbwejEye",
            "score": 733,
            "rank": 37,
            "view": 864,
            "like": 62,
            "danmaku": 0,
            "reply": 6,
            "favorite": 19,
            "coin": 4,
            "share": 1
        },
        {
            "aid": 113093686330378,
            "bvid": "BV1N3HoeEEQk",
            "title": "\u3010\u6d1b\u5929\u4f9d\u4e50\u6b63\u7eebV4\u539f\u521b\u3011\u8ffd\u5fc6\uff0a\u518d\u4f1a\u3010\u76f2\u76d2\u539f\u521b\u66f2\u3011",
            "pubdate": "2024-09-07 21:00:00",
            "author": "\u4e0d\u7f81\u9601Club",
            "mid": 346344929,
            "pickup": "NO",
            "pic": "http://i0.hdslb.com/bfs/archive/bbdce9c7c31cfc7229c3cffe4acef63c78348fa2.jpg",
            "pic_url": "/cover/69/av113093686330378.jpg",
            "url": "https://www.bilibili.com/video/BV1N3HoeEEQk",
            "score": 725,
            "rank": 38,
            "view": 146,
            "like": 25,
            "danmaku": 0,
            "reply": 1,
            "favorite": 14,
            "coin": 11,
            "share": 13
        },
        {
            "aid": 113099927521072,
            "bvid": "BV1APpeeUE5t",
            "title": "\u3010\u4e50\u6b63\u7eebAi&\u4e50\u6b63\u9f99\u7259Ai\u3011\u7956\u7c41\u3010Ace Cover\u3011\u3010\u4e00\u68a6\u6c5f\u6e56\u3011",
            "pubdate": "2024-09-08 14:00:00",
            "author": "\u5de5\u4e1a\u5236\u6e05\u86d9",
            "mid": 20420889,
            "pickup": "NO",
            "pic": "http://i1.hdslb.com/bfs/archive/f4430f1f3468ef58766135d9a92c9b468644064f.jpg",
            "pic_url": "/cover/69/av113099927521072.jpg",
            "url": "https://www.bilibili.com/video/BV1APpeeUE5t",
            "score": 722,
            "rank": 39,
            "view": 299,
            "like": 17,
            "danmaku": 1,
            "reply": 5,
            "favorite": 16,
            "coin": 12,
            "share": 5
        },
        {
            "aid": 113141853718464,
            "bvid": "BV1Nc4Se6E5J",
            "title": "\u3010\u4e50\u6b63\u7eeb\u7ffb\u5531\u3011\u53cc\u4eba\u8239",
            "pubdate": "2024-09-15 21:44:49",
            "author": "\u5927\u62db\u540c\u5b66",
            "mid": 358430948,
            "pickup": "NO",
            "pic": "http://i2.hdslb.com/bfs/archive/e45d6779747abc3fcb6bef67dcf4c51cd4160eac.jpg",
            "pic_url": "/cover/69/av113141853718464.jpg",
            "url": "https://www.bilibili.com/video/BV1Nc4Se6E5J",
            "score": 709,
            "rank": 40,
            "view": 165,
            "like": 26,
            "danmaku": 0,
            "reply": 1,
            "favorite": 16,
            "coin": 6,
            "share": 0
        }
    ],
    "pk": [
        {
            "aid": 113158211635553,
            "bvid": "BV1Fjt5eqEVr",
            "title": "\u3010\u4e50\u6b63\u7eeb\u7ffb\u5531\u3011\u661f\u6d77\u6f2b\u6e38 \u8ddf\u7eeb\u7eeb\u4e00\u8d77\u73a9\u8d5b\u5c14\u53f7\uff01\uff01",
            "pubdate": "2024-09-18 21:05:00",
            "author": "\u6d1b\u96e8\u8fb0P",
            "mid": 402274020,
            "pickup": "PK",
            "pic": "http://i2.hdslb.com/bfs/archive/df6187d3acbb4e3de91b3a9ecbca465fead00b52.jpg",
            "pic_url": "/cover/69/av113158211635553.jpg",
            "url": "https://www.bilibili.com/video/BV1Fjt5eqEVr",
            "score": 1628,
            "rank": 28,
            "view": 451,
            "like": 80,
            "danmaku": 0,
            "reply": 15,
            "favorite": 34,
            "coin": 15,
            "share": 3
        }
    ]
}