{
    "num": 9,
    "total_num": 43,
    "bvid": "BV1Nj41197rH",
    "fb_flag": 1,
    "zb": [
        {
            "aid": 616327019,
            "bvid": "BV1xh4y1V77g",
            "title": "\u3010\u4e50\u6b63\u7eeb\u3011\u661f\u706b\u71c3\u70e7\u5427\u300e\u56fd\u9645\u5171\u8fd0\u53f2\u300f",
            "pubdate": 1690030500,
            "author": "\u5fc3\u9b54\u624d\u4e0d\u662f\u5973\u5b69\u5b50\u5462",
            "mid": 359100532,
            "view": 12765,
            "danmaku": 34,
            "reply": 99,
            "favorite": 1200,
            "coin": 573,
            "share": 102,
            "like": 1618,
            "score": 51692,
            "index": 1,
            "pickup": 0,
            "pic": "http://i1.hdslb.com/bfs/archive/5a65cf7667aa6baaef87865a1ed0535a90e28322.jpg",
            "pubdate_str": "2023-07-22 20:55:00",
            "pic_url": "/cover/9/av616327019.jpg",
            "url": "https://www.bilibili.com/video/BV1xh4y1V77g"
        },
        {
            "aid": 914018206,
            "bvid": "BV15M4y1W7xy",
            "title": "\u3010\u6d1b\u5929\u4f9d\u4e50\u6b63\u7eeb\u539f\u521b\u3011\u7ea2\u5c18\u5bc4\u96ea\u2014\u2014\u201c\u541b\u57cb\u6cc9\u4e0b\u6ce5\u9500\u9aa8\u3002\u201d\u3010\u5357\u5317\u7ec4/\u5439\u7389\u3011",
            "pubdate": 1690635600,
            "author": "\u88ab\u9057\u5fd8\u8005\u7684\u54c0\u4f24",
            "mid": 12836485,
            "view": 2821,
            "danmaku": 39,
            "reply": 156,
            "favorite": 561,
            "coin": 467,
            "share": 51,
            "like": 1004,
            "score": 45015,
            "index": 2,
            "pickup": 0,
            "pic": "http://i2.hdslb.com/bfs/archive/291d4d95bbbd078fd52f9c823468764b96b1dbea.jpg",
            "pubdate_str": "2023-07-29 21:00:00",
            "pic_url": "/cover/9/av914018206.jpg",
            "url": "https://www.bilibili.com/video/BV15M4y1W7xy"
        },
        {
            "aid": 829073139,
            "bvid": "BV1fu4y127DE",
            "title": "\u3010\u6d1b\u5929\u4f9d&\u4e50\u6b63\u7eeb\u539f\u521b\u66f2\u3011Attachment\u3010\u5357\u5317\u7ec4\u590f\u65e5\u6b4c\u4f1a\u5355\u54c1\u3011",
            "pubdate": 1690635600,
            "author": "\u8424\u5931Hinano",
            "mid": 567708,
            "view": 1996,
            "danmaku": 1,
            "reply": 70,
            "favorite": 420,
            "coin": 262,
            "share": 25,
            "like": 715,
            "score": 31715,
            "index": 3,
            "pickup": 0,
            "pic": "http://i0.hdslb.com/bfs/archive/7c9b456d65f6c010feb400cbffb68676e18997e8.jpg",
            "pubdate_str": "2023-07-29 21:00:00",
            "pic_url": "/cover/9/av829073139.jpg",
            "url": "https://www.bilibili.com/video/BV1fu4y127DE"
        },
        {
            "aid": 231491409,
            "bvid": "BV12841117Cw",
            "title": "\u3010\u6d1b\u5929\u4f9d/\u4e50\u6b63\u7eeb\u539f\u521b\u3011\u6795\u65e7\u4e66\u3010PV\u4ed8\u3011",
            "pubdate": 1690542000,
            "author": "Luckkoi-",
            "mid": 432745893,
            "view": 1810,
            "danmaku": 2,
            "reply": 55,
            "favorite": 383,
            "coin": 238,
            "share": 29,
            "like": 521,
            "score": 28343,
            "index": 4,
            "pickup": 0,
            "pic": "http://i0.hdslb.com/bfs/archive/784191aa25a787cee8098e98eccbaa8064de5359.jpg",
            "pubdate_str": "2023-07-28 19:00:00",
            "pic_url": "/cover/9/av231491409.jpg",
            "url": "https://www.bilibili.com/video/BV12841117Cw"
        },
        {
            "aid": 786251719,
            "bvid": "BV1f14y1Q7qF",
            "title": "\u3010\u6d1b\u5929\u4f9d\u00d7\u8a00\u548c\u00d7\u4e50\u6b63\u7eeb AI\u3011\u4e2d\u6587\u586b\u8bcd\uff01\u4e2dV\u4e09\u5de8\u5934\u5143\u6c14\u7ffb\u5531\u300aMore! Jump! More!\u300b | \u30e2\u30a2\uff01\u30b8\u30e3\u30f3\u30d7\uff01\u30e2\u30a2\uff01\u3010ACE COVER\u3011",
            "pubdate": 1690196400,
            "author": "\u6d69\u6cbb_CloverP",
            "mid": 10969904,
            "view": 4729,
            "danmaku": 2,
            "reply": 71,
            "favorite": 504,
            "coin": 149,
            "share": 85,
            "like": 1253,
            "score": 24685,
            "index": 5,
            "pickup": 0,
            "pic": "http://i1.hdslb.com/bfs/archive/092d9e1eaa12225341f84b0d621a2dbde482d8ea.jpg",
            "pubdate_str": "2023-07-24 19:00:00",
            "pic_url": "/cover/9/av786251719.jpg",
            "url": "https://www.bilibili.com/video/BV1f14y1Q7qF"
        },
        {
            "aid": 616469414,
            "bvid": "BV1Jh4y157dB",
            "title": "\u3010TNO\u3011\u906e\u5929\u853d\u65e5\u7684\u300a\u9ed1\u9e1f\u300b\uff0c\u5728\u661f\u706b\u91cc\u5f25\u6563",
            "pubdate": 1690452000,
            "author": "\u7d0d\u862d\u601d\u7434",
            "mid": 418267553,
            "view": 6265,
            "danmaku": 4,
            "reply": 63,
            "favorite": 521,
            "coin": 286,
            "share": 29,
            "like": 709,
            "score": 22996,
            "index": 6,
            "pickup": 0,
            "pic": "http://i2.hdslb.com/bfs/archive/ac8f30c7c21fa4628b2be6f737cd24db4c778adc.jpg",
            "pubdate_str": "2023-07-27 18:00:00",
            "pic_url": "/cover/9/av616469414.jpg",
            "url": "https://www.bilibili.com/video/BV1Jh4y157dB"
        },
        {
            "aid": 358960462,
            "bvid": "BV1nX4y1E7bV",
            "title": "\u3010\u4e50\u6b63\u5144\u59b9\u539f\u521b\u3011\u97f3\u5f8b\u88ab\u6298\u53e0\uff0c\u8e0f\u5165\u300a\u6c38\u6052\u7eaa\u5143\u300b\u2014\u2014\u201c\u7528\u65cb\u5f8b\u5c06\u7231\u6b4c\u5531\uff0c\u6240\u5199\u662f\u5fc3\u4e2d\u6240\u60f3\u201d",
            "pubdate": 1690362000,
            "author": "\u95ea\u5149\u821e\u59ec\u795e\u732b",
            "mid": 3872300,
            "view": 1428,
            "danmaku": 77,
            "reply": 49,
            "favorite": 234,
            "coin": 110,
            "share": 27,
            "like": 343,
            "score": 13969,
            "index": 7,
            "pickup": 0,
            "pic": "http://i2.hdslb.com/bfs/archive/ccb28e47b00e1e1c51a9548fb537c685840dcd39.jpg",
            "pubdate_str": "2023-07-26 17:00:00",
            "pic_url": "/cover/9/av358960462.jpg",
            "url": "https://www.bilibili.com/video/BV1nX4y1E7bV"
        },
        {
            "aid": 361263772,
            "bvid": "BV1f94y1e7ec",
            "title": "\u3010\u4e50\u6b63\u7eebAI\u65e5\u8bed\u3011\u7ae5\u796d\uff5eInnocent Treasures\u3010\u4e1c\u65b9VOCALOID\u3011",
            "pubdate": 1690257600,
            "author": "\u7a7a\u306e\u8272\u6c34\u306e\u8272",
            "mid": 306722896,
            "view": 2051,
            "danmaku": 6,
            "reply": 58,
            "favorite": 253,
            "coin": 157,
            "share": 31,
            "like": 348,
            "score": 13673,
            "index": 8,
            "pickup": 0,
            "pic": "http://i0.hdslb.com/bfs/archive/9de04abac4396c94223c1464467cd43f999edbf4.jpg",
            "pubdate_str": "2023-07-25 12:00:00",
            "pic_url": "/cover/9/av361263772.jpg",
            "url": "https://www.bilibili.com/video/BV1f94y1e7ec"
        },
        {
            "aid": 998730660,
            "bvid": "BV1ax4y1d7T2",
            "title": "\u3010\u4e50\u6b63\u7eebAI\u3011\u8d85\u71c3\u539f\u521b\u53e4\u98ceRAP\u300a\u70c8\u706b\u711a\u5c71\u300b\u6cb8\u7f8a\u7f8a\u89d2\u8272\u66f2",
            "pubdate": 1689955200,
            "author": "\u6c90\u5b50\u8427",
            "mid": 19126383,
            "view": 3032,
            "danmaku": 83,
            "reply": 29,
            "favorite": 234,
            "coin": 239,
            "share": 51,
            "like": 535,
            "score": 12906,
            "index": 9,
            "pickup": 0,
            "pic": "http://i2.hdslb.com/bfs/archive/d6a08bf2dfaacad7a13f0e35f8d69be213f6dcca.jpg",
            "pubdate_str": "2023-07-22 00:00:00",
            "pic_url": "/cover/9/av998730660.jpg",
            "url": "https://www.bilibili.com/video/BV1ax4y1d7T2"
        },
        {
            "aid": 404086052,
            "bvid": "BV1FV41157PW",
            "title": "\u3010\u6d1b\u5929\u4f9d&\u4e50\u6b63\u7eeb\u539f\u521b\u3011\u6298\u5b50\u620f\u3010\u5357\u5317\u7ec4/pv\u4ed8\u3011",
            "pubdate": 1690635600,
            "author": "_\u767d\u7802\u68e0",
            "mid": 37267098,
            "view": 466,
            "danmaku": 2,
            "reply": 39,
            "favorite": 130,
            "coin": 61,
            "share": 10,
            "like": 175,
            "score": 9039,
            "index": 10,
            "pickup": 0,
            "pic": "http://i0.hdslb.com/bfs/archive/3eb7427e42d103e191a0bcfc9fd714958a4e1db3.jpg",
            "pubdate_str": "2023-07-29 21:00:00",
            "pic_url": "/cover/9/av404086052.jpg",
            "url": "https://www.bilibili.com/video/BV1FV41157PW"
        },
        {
            "aid": 231164110,
            "bvid": "BV1t8411S74H",
            "title": "\u3010TNO\u82f1\u683c\u5170\u3011\u82f1\u683c\u5170\u7684\u767e\u5408\u82b1\uff0c\u5728\u96e8\u4e2d\u300a\u6ef4\u7b54\u6ef4\u7b54\u300b",
            "pubdate": 1689836400,
            "author": "\u72ec\u8d70\u519b\u90e8\u9ea6\u51ef\u6492",
            "mid": 361123115,
            "view": 4180,
            "danmaku": 4,
            "reply": 12,
            "favorite": 214,
            "coin": 166,
            "share": 82,
            "like": 189,
            "score": 8932,
            "index": 11,
            "pickup": 0,
            "pic": "http://i0.hdslb.com/bfs/archive/e670ced7ed94a27bcac9ac2c3e29d9204c3ed23c.jpg",
            "pubdate_str": "2023-07-20 15:00:00",
            "pic_url": "/cover/9/av231164110.jpg",
            "url": "https://www.bilibili.com/video/BV1t8411S74H"
        },
        {
            "aid": 658847369,
            "bvid": "BV1xh4y1y7MK",
            "title": "\u3010XU\u96c4\u72ee\u53db\u4e71\u586b\u8bcd\u3011\u96c4\u72ee\u5ba3\u8a00",
            "pubdate": 1690123913,
            "author": "\u9769\u6cd5\u7b2c\u4e00\u7a81\u7834\u624bElaina",
            "mid": 525741876,
            "view": 4377,
            "danmaku": 3,
            "reply": 59,
            "favorite": 194,
            "coin": 96,
            "share": 31,
            "like": 305,
            "score": 8576,
            "index": 12,
            "pickup": 0,
            "pic": "http://i2.hdslb.com/bfs/archive/37838084976c6cec777fa8f78a9855cfb784d2d0.jpg",
            "pubdate_str": "2023-07-23 22:51:53",
            "pic_url": "/cover/9/av658847369.jpg",
            "url": "https://www.bilibili.com/video/BV1xh4y1y7MK"
        },
        {
            "aid": 829074303,
            "bvid": "BV1fu4y127zG",
            "title": "\u3010\u4e50\u6b63\u7eebAI\u539f\u521b\u3011\u9ed1\u767d\u7535\u5f71",
            "pubdate": 1690571528,
            "author": "\u5931\u4e50\u56edp",
            "mid": 1699566930,
            "view": 571,
            "danmaku": 1,
            "reply": 32,
            "favorite": 113,
            "coin": 68,
            "share": 5,
            "like": 143,
            "score": 8155,
            "index": 13,
            "pickup": 0,
            "pic": "http://i0.hdslb.com/bfs/archive/1504e6d4ea8bc6348e993c1117fcd024b31e03d0.jpg",
            "pubdate_str": "2023-07-29 03:12:08",
            "pic_url": "/cover/9/av829074303.jpg",
            "url": "https://www.bilibili.com/video/BV1fu4y127zG"
        },
        {
            "aid": 956119286,
            "bvid": "BV1sW4y1d7nN",
            "title": "\u3010\u6d1b\u5929\u4f9d/\u4e50\u6b63\u7eeb\u3011\u300a\u5065\u5c06\u300b\u201c\u54c7\u585e\uff0c\u6211\u7684\u59ec\u8089\u600e\u4e48\u90a3\u4e48\u7684\u597d\u770b\uff1f\u201d",
            "pubdate": 1689609740,
            "author": "\u9583\u96fb_P",
            "mid": 1367050036,
            "view": 6129,
            "danmaku": 23,
            "reply": 103,
            "favorite": 149,
            "coin": 103,
            "share": 424,
            "like": 664,
            "score": 7633,
            "index": 14,
            "pickup": 0,
            "pic": "http://i2.hdslb.com/bfs/archive/fd1e7c752bd466654a369e4559b17d7e6e0b40cb.jpg",
            "pubdate_str": "2023-07-18 00:02:20",
            "pic_url": "/cover/9/av956119286.jpg",
            "url": "https://www.bilibili.com/video/BV1sW4y1d7nN"
        },
        {
            "aid": 273574155,
            "bvid": "BV1CF411Q7rM",
            "title": "\u3010\u6d1b\u5929\u4f9d/\u4e50\u6b63\u7eeb\u539f\u521b\u3011\u661f\u660e\u3010JUSF\u5468\u5b58719\u6295\u7a3f11\u5468\u5e74\u8d3a\u66f2\u3011",
            "pubdate": 1689765600,
            "author": "\u865a\u62df\u70e4\u7bb1\u6574\u6d3b\u7ec4",
            "mid": 1275241129,
            "view": 1849,
            "danmaku": 7,
            "reply": 11,
            "favorite": 135,
            "coin": 65,
            "share": 50,
            "like": 212,
            "score": 5717,
            "index": 15,
            "pickup": 0,
            "pic": "http://i2.hdslb.com/bfs/archive/2da3df3a4ce9e4aeba7e3bd740cebd78ebc285a7.jpg",
            "pubdate_str": "2023-07-19 19:20:00",
            "pic_url": "/cover/9/av273574155.jpg",
            "url": "https://www.bilibili.com/video/BV1CF411Q7rM"
        },
        {
            "aid": 446452353,
            "bvid": "BV1mj411X7M4",
            "title": "\u3010\u4e50\u6b63\u7eebAI\u3011\u661f\u5c18\u4e2d\u7684\u65c5\u4eba\u3010ACE COVER\u3011",
            "pubdate": 1690459200,
            "author": "injection-",
            "mid": 1764810,
            "view": 368,
            "danmaku": 3,
            "reply": 37,
            "favorite": 73,
            "coin": 48,
            "share": 3,
            "like": 90,
            "score": 5408,
            "index": 16,
            "pickup": 0,
            "pic": "http://i1.hdslb.com/bfs/archive/70d2266e8e08b3877dd330b3fa5c6819a07cb755.jpg",
            "pubdate_str": "2023-07-27 20:00:00",
            "pic_url": "/cover/9/av446452353.jpg",
            "url": "https://www.bilibili.com/video/BV1mj411X7M4"
        },
        {
            "aid": 786485012,
            "bvid": "BV1v14y1z7PL",
            "title": "\u3010\u4e50\u6b63\u7eebAI\u539f\u521b\u3011\u9910\u524d\u7948\u7977",
            "pubdate": 1690299028,
            "author": "\u5931\u4e50\u56edp",
            "mid": 1699566930,
            "view": 908,
            "danmaku": 1,
            "reply": 22,
            "favorite": 103,
            "coin": 52,
            "share": 3,
            "like": 155,
            "score": 5160,
            "index": 17,
            "pickup": 0,
            "pic": "http://i1.hdslb.com/bfs/archive/d15964f23e5a7eabc8ce75d7e3d3a09ac679789c.jpg",
            "pubdate_str": "2023-07-25 23:30:28",
            "pic_url": "/cover/9/av786485012.jpg",
            "url": "https://www.bilibili.com/video/BV1v14y1z7PL"
        },
        {
            "aid": 998631662,
            "bvid": "BV1cx4y1d7zH",
            "title": "\u3010\u4e50\u6b63\u7eeb\u3011\u516c\u793edisco\uff08PV\u91cd\u7f6e\uff09",
            "pubdate": 1690468329,
            "author": "CLRS_REED",
            "mid": 400991742,
            "view": 2387,
            "danmaku": 1,
            "reply": 27,
            "favorite": 114,
            "coin": 28,
            "share": 9,
            "like": 190,
            "score": 4517,
            "index": 18,
            "pickup": 0,
            "pic": "http://i1.hdslb.com/bfs/archive/be45237b8018d6941aac8e31bedb6306dc2a025b.jpg",
            "pubdate_str": "2023-07-27 22:32:09",
            "pic_url": "/cover/9/av998631662.jpg",
            "url": "https://www.bilibili.com/video/BV1cx4y1d7zH"
        },
        {
            "aid": 829091027,
            "bvid": "BV19u4y127GM",
            "title": "\u6765\u751f\u620f\u2014\u2014\u4e50\u6b63\u7eeb\uff08V3\uff09",
            "pubdate": 1690548112,
            "author": "\u65f6\u6d25\u6cea",
            "mid": 106628316,
            "view": 579,
            "danmaku": 1,
            "reply": 21,
            "favorite": 62,
            "coin": 71,
            "share": 10,
            "like": 117,
            "score": 4201,
            "index": 19,
            "pickup": 0,
            "pic": "http://i0.hdslb.com/bfs/archive/ba354c8d9be1422221ad242d2dc61c39e85c3351.jpg",
            "pubdate_str": "2023-07-28 20:41:52",
            "pic_url": "/cover/9/av829091027.jpg",
            "url": "https://www.bilibili.com/video/BV19u4y127GM"
        },
        {
            "aid": 914085048,
            "bvid": "BV1iM4y1W7hX",
            "title": "[\u4e50\u6b63\u7eeb\u539f\u521b]\u300a\u4e4c\u4e91\u300b\u603b\u6709\u4eba\u8fd8\u613f\u62e5\u62b1\u8fd9\u4e16\u754c",
            "pubdate": 1690520856,
            "author": "\u4f11\u6b62\u7b26TheRest",
            "mid": 502187371,
            "view": 423,
            "danmaku": 3,
            "reply": 22,
            "favorite": 63,
            "coin": 36,
            "share": 2,
            "like": 87,
            "score": 3719,
            "index": 20,
            "pickup": 0,
            "pic": "http://i0.hdslb.com/bfs/archive/94b95e630f1167ce2f06d9af43a62e5f7541660c.jpg",
            "pubdate_str": "2023-07-28 13:07:36",
            "pic_url": "/cover/9/av914085048.jpg",
            "url": "https://www.bilibili.com/video/BV1iM4y1W7hX"
        }
    ],
    "fb": [
        {
            "aid": 743807019,
            "bvid": "BV1Sk4y1G7kp",
            "title": "\u3010TNO\u3011\u3010\u4e50\u6b63\u7eeb\u00d7\u6d1b\u5929\u4f9d\u3011\u9ed1\u6697\u5927\u9646\u4e0a\u7684\u300a\u611f\u4f24\u6218\u4e89\u300b\uff08\u6362\u6e90\u7248\uff0c\u5802\u5802\u590d\u6d3b\uff09",
            "pubdate": 1690170620,
            "author": "kfk\u706b\u817f\u80a0",
            "mid": 387832219,
            "view": 1289,
            "danmaku": 3,
            "reply": 15,
            "favorite": 82,
            "coin": 11,
            "share": 2,
            "like": 99,
            "score": 2953,
            "index": 21,
            "pickup": 0,
            "pic": "http://i0.hdslb.com/bfs/archive/9bd7c2fc3c666ae9981e986487e5cac7659f7a7a.jpg",
            "pubdate_str": "2023-07-24 11:50:20",
            "pic_url": "/cover/9/av743807019.jpg",
            "url": "https://www.bilibili.com/video/BV1Sk4y1G7kp"
        },
        {
            "aid": 615980297,
            "bvid": "BV1gh4y177bC",
            "title": "\u3010\u4e50\u6b63\u7eebAI\u3011\u300a\u9047\u89c1\u300b\u2014\u2014\u201c\u6211\u9047\u89c1\u8c01\uff0c\u4f1a\u6709\u600e\u6837\u7684\u5bf9\u767d\u201d\u3010HB To \u6d41\u6b87\u6653\u8424\u3011",
            "pubdate": 1689566400,
            "author": "\u96e8\u5df7\u72ec\u914cRainfall",
            "mid": 341906317,
            "view": 934,
            "danmaku": 0,
            "reply": 2,
            "favorite": 65,
            "coin": 46,
            "share": 17,
            "like": 86,
            "score": 2794,
            "index": 22,
            "pickup": 0,
            "pic": "http://i1.hdslb.com/bfs/archive/1bf413bacf7c213ecb2ef94957829daaf0a5adaa.jpg",
            "pubdate_str": "2023-07-17 12:00:00",
            "pic_url": "/cover/9/av615980297.jpg",
            "url": "https://www.bilibili.com/video/BV1gh4y177bC"
        },
        {
            "aid": 658961190,
            "bvid": "BV1Dh4y1y7Ra",
            "title": "whispering snowflakes \u3010\u4e50\u6b63\u7eeb & \u6d1b\u5929\u4f9d\u3011\u7eaf\u767d\u7684\u8c0e\u8a00 \u662f\u4f60\u6211\u4e0d\u66fe\u8a00\u8bf4\u7684\u4f4e\u8bed \u5357\u5317\u7ec4\u503e\u5531 \u7ffb\u8c03 cover \u3010\u661f\u5c18 & \u6d77\u4f0a\u3011",
            "pubdate": 1690367573,
            "author": "\u4e91\u9645\u70c1\u6708",
            "mid": 197612416,
            "view": 903,
            "danmaku": 2,
            "reply": 27,
            "favorite": 73,
            "coin": 8,
            "share": 7,
            "like": 80,
            "score": 2744,
            "index": 23,
            "pickup": 0,
            "pic": "http://i2.hdslb.com/bfs/archive/d22a38a72295d9c76ff2a5599c2e8bbcf51ddcb8.jpg",
            "pubdate_str": "2023-07-26 18:32:53",
            "pic_url": "/cover/9/av658961190.jpg",
            "url": "https://www.bilibili.com/video/BV1Dh4y1y7Ra"
        },
        {
            "aid": 998976921,
            "bvid": "BV1Lx4y1R7iF",
            "title": "\u3010\u6d1b\u5929\u4f9d/\u4e50\u6b63\u7eeb\u539f\u521b\u3011\u300a\u9177\u9177\u7684\u6211\uff0c\u5531\u7740\u9177\u9177\u7684\u6b4c\u300b",
            "pubdate": 1690371000,
            "author": "\u82b1\u56edGARDEN_",
            "mid": 3493277892348060,
            "view": 506,
            "danmaku": 1,
            "reply": 19,
            "favorite": 52,
            "coin": 22,
            "share": 5,
            "like": 103,
            "score": 2563,
            "index": 24,
            "pickup": 1,
            "pic": "http://i2.hdslb.com/bfs/archive/59c68cbb0619f129b424fe26f2051780848bd0df.jpg",
            "pubdate_str": "2023-07-26 19:30:00",
            "pic_url": "/cover/9/av998976921.jpg",
            "url": "https://www.bilibili.com/video/BV1Lx4y1R7iF"
        },
        {
            "aid": 316410972,
            "bvid": "BV1xP411z7zo",
            "title": "\u3010\u4e50\u6b63\u7eeb&\u4e50\u6b63\u9f99\u7259\u3011\u81f4 \u9eef\u6de1\u661f\u3010ACE COVER\u3011",
            "pubdate": 1690365600,
            "author": "Dagazs",
            "mid": 88726438,
            "view": 543,
            "danmaku": 2,
            "reply": 22,
            "favorite": 52,
            "coin": 24,
            "share": 1,
            "like": 78,
            "score": 2435,
            "index": 25,
            "pickup": 0,
            "pic": "http://i2.hdslb.com/bfs/archive/cdd0adcc852f2ca3c5248bc13edf32e9316b8bbe.jpg",
            "pubdate_str": "2023-07-26 18:00:00",
            "pic_url": "/cover/9/av316410972.jpg",
            "url": "https://www.bilibili.com/video/BV1xP411z7zo"
        },
        {
            "aid": 701335554,
            "bvid": "BV1km4y1L7sV",
            "title": "\u4e5d\u4e07\u5b57\u2014\u2014\u4e50\u6b63\u7eeb\uff08ACE\uff09",
            "pubdate": 1690132951,
            "author": "\u65f6\u6d25\u6cea",
            "mid": 106628316,
            "view": 483,
            "danmaku": 0,
            "reply": 15,
            "favorite": 47,
            "coin": 26,
            "share": 1,
            "like": 76,
            "score": 2294,
            "index": 26,
            "pickup": 0,
            "pic": "http://i2.hdslb.com/bfs/archive/5436c7b443a531d5ca3f05e944c73cac52f6dbce.jpg",
            "pubdate_str": "2023-07-24 01:22:31",
            "pic_url": "/cover/9/av701335554.jpg",
            "url": "https://www.bilibili.com/video/BV1km4y1L7sV"
        },
        {
            "aid": 701243439,
            "bvid": "BV1Lm4y1L75n",
            "title": "\u3010\u4e50\u6b63\u5144\u59b9\u5728\u7ebf\u8e66\u8fea\u3011\u4f60\u6ca1\u6709\u6253\u706b\u673a\u2014\u2014\u300a\u4e2d\u610f\u4f60\u300b\u3010ACE Studio Cover\u3011",
            "pubdate": 1690017600,
            "author": "\u66ae\u8272\u672a\u91cf",
            "mid": 272904686,
            "view": 831,
            "danmaku": 1,
            "reply": 22,
            "favorite": 52,
            "coin": 19,
            "share": 18,
            "like": 116,
            "score": 2270,
            "index": 27,
            "pickup": 0,
            "pic": "http://i2.hdslb.com/bfs/archive/df661c78268a575164b22ee35d6a1535f4e4da17.jpg",
            "pubdate_str": "2023-07-22 17:20:00",
            "pic_url": "/cover/9/av701243439.jpg",
            "url": "https://www.bilibili.com/video/BV1Lm4y1L75n"
        },
        {
            "aid": 403862953,
            "bvid": "BV1YV411L7yG",
            "title": "\u3010\u8a00\u548c&\u4e50\u6b63\u7eeb\u3011\u661f\u5c18\u4e2d\u7684\u65c5\u4eba\u3010ACE COVER\u3011",
            "pubdate": 1690089146,
            "author": "\u6c2f\u79bb\u5b50P",
            "mid": 428330736,
            "view": 366,
            "danmaku": 0,
            "reply": 10,
            "favorite": 47,
            "coin": 13,
            "share": 2,
            "like": 51,
            "score": 2260,
            "index": 28,
            "pickup": 0,
            "pic": "http://i2.hdslb.com/bfs/archive/7b012708c3e1d93a588c0bdb62c94e077b21538e.jpg",
            "pubdate_str": "2023-07-23 13:12:26",
            "pic_url": "/cover/9/av403862953.jpg",
            "url": "https://www.bilibili.com/video/BV1YV411L7yG"
        },
        {
            "aid": 273772132,
            "bvid": "BV1mc411c74y",
            "title": "\u3010\u4e50\u6b63\u7eebAI\u3011\u201c\u51b3\u5b9a\u672c\u8d28\u7684\uff0c\u662f\u6211\u3002\u201d- \u300a\u74f6\u4e2d\u5bf9\u51b3\u300b\u3010ACE StudioCOVER\u3011\u3010noaiy\u3011",
            "pubdate": 1690175304,
            "author": "\u8bfa\u88d4\u57b8\u30ce\u30a2\u30a4\u30e6",
            "mid": 482592218,
            "view": 801,
            "danmaku": 0,
            "reply": 11,
            "favorite": 42,
            "coin": 22,
            "share": 0,
            "like": 76,
            "score": 1866,
            "index": 29,
            "pickup": 0,
            "pic": "http://i0.hdslb.com/bfs/archive/f480e50935c7aa1c4bb70cdc9886d6a3bdd8b730.jpg",
            "pubdate_str": "2023-07-24 13:08:24",
            "pic_url": "/cover/9/av273772132.jpg",
            "url": "https://www.bilibili.com/video/BV1mc411c74y"
        },
        {
            "aid": 786262655,
            "bvid": "BV1X14y1Q7mb",
            "title": "\u7eff\u65cb\u98ce\u2014\u2014\u4e50\u6b63\u7eeb\uff0c\u4e50\u6b63\u9f99\u7259\uff08\u7ffb\u5531\uff09",
            "pubdate": 1690207670,
            "author": "\u65f6\u6d25\u6cea",
            "mid": 106628316,
            "view": 358,
            "danmaku": 1,
            "reply": 17,
            "favorite": 36,
            "coin": 21,
            "share": 1,
            "like": 56,
            "score": 1791,
            "index": 30,
            "pickup": 0,
            "pic": "http://i1.hdslb.com/bfs/archive/0beed4e70158efcc8365264d71ae1f4e2470d0b2.jpg",
            "pubdate_str": "2023-07-24 22:07:50",
            "pic_url": "/cover/9/av786262655.jpg",
            "url": "https://www.bilibili.com/video/BV1X14y1Q7mb"
        },
        {
            "aid": 743988021,
            "bvid": "BV19k4y1g7Rb",
            "title": "\u3010\u6d1b\u5929\u4f9d\u4e50\u6b63\u7eeb\u539f\u521b\u3011\u7f2a\u65af\u7684\u665a\u9910",
            "pubdate": 1690467593,
            "author": "\u6dcc\u5149P",
            "mid": 2012382444,
            "view": 748,
            "danmaku": 0,
            "reply": 26,
            "favorite": 34,
            "coin": 20,
            "share": 16,
            "like": 90,
            "score": 1737,
            "index": 31,
            "pickup": 0,
            "pic": "http://i0.hdslb.com/bfs/archive/c8b6adc73ce3e267a983e86b331956a5c7fb391c.jpg",
            "pubdate_str": "2023-07-27 22:19:53",
            "pic_url": "/cover/9/av743988021.jpg",
            "url": "https://www.bilibili.com/video/BV19k4y1g7Rb"
        },
        {
            "aid": 616340795,
            "bvid": "BV1Bh4y1V7dr",
            "title": "\u3010\u6d1b\u5929\u4f9d\u00b7\u4e50\u6b63\u7eebACE\u3011\u4e00\u573a\u843d\u82b1\u96e8,\u4e0b\u5f97\u591a\u75f4\u7f20\u2014\u300a\u843d\u82b1\u96e8\u300b\u91cd\u7f6e\u6765\u5566!\u8d85\u4f18\u7f8e\u7684\u6781\u81f4\u9ad8\u97f3!",
            "pubdate": 1690596000,
            "author": "\u6211Aaron_779",
            "mid": 433810937,
            "view": 301,
            "danmaku": 3,
            "reply": 16,
            "favorite": 35,
            "coin": 7,
            "share": 2,
            "like": 60,
            "score": 1607,
            "index": 32,
            "pickup": 0,
            "pic": "http://i1.hdslb.com/bfs/archive/b3b2c1b402702ed218641aa3dc47af4c6014a1af.jpg",
            "pubdate_str": "2023-07-29 10:00:00",
            "pic_url": "/cover/9/av616340795.jpg",
            "url": "https://www.bilibili.com/video/BV1Bh4y1V7dr"
        },
        {
            "aid": 913832967,
            "bvid": "BV1fM4y1s7Eq",
            "title": "\u3010\u4e50\u6b63\u7eeb\u3011\u5931\u8d25\u4f5c\u79e6\u738b",
            "pubdate": 1690466899,
            "author": "CLRS_REED",
            "mid": 400991742,
            "view": 1068,
            "danmaku": 0,
            "reply": 10,
            "favorite": 34,
            "coin": 14,
            "share": 1,
            "like": 78,
            "score": 1451,
            "index": 33,
            "pickup": 0,
            "pic": "http://i1.hdslb.com/bfs/archive/267d812eef4660fa47237ecf898a5c1964e7f071.jpg",
            "pubdate_str": "2023-07-27 22:08:19",
            "pic_url": "/cover/9/av913832967.jpg",
            "url": "https://www.bilibili.com/video/BV1fM4y1s7Eq"
        },
        {
            "aid": 871016160,
            "bvid": "BV1ZV4y1b7A8",
            "title": "\u3010\u4e50\u6b63\u7eebAI English\u3011\u300aRemember the Summer\u300b\u2014\u2014\u8bf7\u5c06\u4eca\u590f\u6c38\u8fdc\u94ed\u8bb0",
            "pubdate": 1689670800,
            "author": "KunKi114514",
            "mid": 163104011,
            "view": 243,
            "danmaku": 1,
            "reply": 5,
            "favorite": 31,
            "coin": 8,
            "share": 6,
            "like": 23,
            "score": 1426,
            "index": 34,
            "pickup": 0,
            "pic": "http://i0.hdslb.com/bfs/archive/73366e23c1018bb4fce517daa9eb825dd7cf5ef5.jpg",
            "pubdate_str": "2023-07-18 17:00:00",
            "pic_url": "/cover/9/av871016160.jpg",
            "url": "https://www.bilibili.com/video/BV1ZV4y1b7A8"
        },
        {
            "aid": 573692261,
            "bvid": "BV1Qz4y1476j",
            "title": "\u3010\u6d1b\u5929\u4f9d&\u4e50\u6b63\u7eeb\u539f\u521b\u3011\u5766\u8bda\uff08\u9080\u4f60\u5171\u6211\u5c06\u771f\u631a\u5199\u4f5c\u8352\u8bde\u6b4c\u8bd7\uff09\u3010X&Y/\u4e03\u5468\u5e74\u7eaa\u5ff5\u66f2 C\u9762\u3011",
            "pubdate": 1689923100,
            "author": "\u4e36\u4fe1\u5f26",
            "mid": 74122268,
            "view": 456,
            "danmaku": 0,
            "reply": 4,
            "favorite": 36,
            "coin": 9,
            "share": 11,
            "like": 52,
            "score": 1390,
            "index": 35,
            "pickup": 0,
            "pic": "http://i1.hdslb.com/bfs/archive/83b24d746480fc8cbc018109a1b8fc32a1d30725.jpg",
            "pubdate_str": "2023-07-21 15:05:00",
            "pic_url": "/cover/9/av573692261.jpg",
            "url": "https://www.bilibili.com/video/BV1Qz4y1476j"
        },
        {
            "aid": 744021627,
            "bvid": "BV1Pk4y137Lw",
            "title": "\u3010\u6d1b\u5929\u4f9dAI & \u4e50\u6b63\u7eebAI\u3011\u300c\u767d\u77f3\u6eaa\u300d\u7554\uff0c\u4e0e\u4f60\u5171\u6c90\u6625\u79cb\uff1b\u6ee2\u6eaa\u6f7a\u6f7a\uff0c\u5171\u4f60\u708a\u70df\u60a0\u60a0\u3002",
            "pubdate": 1690636500,
            "author": "\u6d1b\u7fbd\u7eebAya_Hata",
            "mid": 1305665901,
            "view": 119,
            "danmaku": 1,
            "reply": 17,
            "favorite": 20,
            "coin": 9,
            "share": 2,
            "like": 37,
            "score": 1243,
            "index": 36,
            "pickup": 0,
            "pic": "http://i2.hdslb.com/bfs/archive/ba61c7443dcc1451346950868f20848b066cf234.jpg",
            "pubdate_str": "2023-07-29 21:15:00",
            "pic_url": "/cover/9/av744021627.jpg",
            "url": "https://www.bilibili.com/video/BV1Pk4y137Lw"
        },
        {
            "aid": 446076203,
            "bvid": "BV1Wj411o7VC",
            "title": "\u3010\u5357\u5317\u7ec4AI\u3011\u590f\u65e5\u5f80\u8fd4\u3010\u4e0e\u5929\u4f9d\u548c\u963f\u7eeb\u5ea6\u8fc7\u4e00\u4e2a\u5feb\u4e50\u6e05\u51c9\u7684\u590f\u5929\u5427\u3011",
            "pubdate": 1689510449,
            "author": "\u4e0d\u53ef\u601dRezerova",
            "mid": 509218761,
            "view": 180,
            "danmaku": 0,
            "reply": 6,
            "favorite": 24,
            "coin": 4,
            "share": 14,
            "like": 31,
            "score": 1135,
            "index": 37,
            "pickup": 0,
            "pic": "http://i2.hdslb.com/bfs/archive/1e08d79e1fed593020f346f55649ee5cc530f9ce.jpg",
            "pubdate_str": "2023-07-16 20:27:29",
            "pic_url": "/cover/9/av446076203.jpg",
            "url": "https://www.bilibili.com/video/BV1Wj411o7VC"
        },
        {
            "aid": 955981701,
            "bvid": "BV1pW4y1Z7CQ",
            "title": "\u3010\u4e50\u6b63\u7eebAI\u3011\u300a\u5bd2\u5c71\u5ba2\u300b\u2014\u2014\u201c\u613f\u5411\u4eba\u95f4\uff0c\u4e0d\u505a\u84ec\u83b1\u5ba2\u201d\u3010HB To \u5f18\u666f\u5929\u3011",
            "pubdate": 1689498000,
            "author": "\u96e8\u5df7\u72ec\u914cRainfall",
            "mid": 341906317,
            "view": 563,
            "danmaku": 0,
            "reply": 9,
            "favorite": 22,
            "coin": 12,
            "share": 13,
            "like": 26,
            "score": 1000,
            "index": 38,
            "pickup": 0,
            "pic": "http://i2.hdslb.com/bfs/archive/176f73aed93975718c854fae398faf39f1498d36.jpg",
            "pubdate_str": "2023-07-16 17:00:00",
            "pic_url": "/cover/9/av955981701.jpg",
            "url": "https://www.bilibili.com/video/BV1pW4y1Z7CQ"
        },
        {
            "aid": 913677953,
            "bvid": "BV1nM4y1s79v",
            "title": "\u72ec\u5c5e\u4e8eAI\u7684\u300a\u4e07\u8c61\u971c\u5929\u300b\u3010\u4e50\u6b63\u7eebAI&\u8a00\u548cAI\u3011\uff08Hi-Res\uff09\u3010ACE COVER\u3011",
            "pubdate": 1689775200,
            "author": "\u753b\u98ce\u4eba_official",
            "mid": 526903186,
            "view": 288,
            "danmaku": 1,
            "reply": 8,
            "favorite": 20,
            "coin": 8,
            "share": 14,
            "like": 42,
            "score": 893,
            "index": 39,
            "pickup": 0,
            "pic": "http://i2.hdslb.com/bfs/archive/fd678f50c3778ff1d653e4a509a4c04515bfb314.jpg",
            "pubdate_str": "2023-07-19 22:00:00",
            "pic_url": "/cover/9/av913677953.jpg",
            "url": "https://www.bilibili.com/video/BV1nM4y1s79v"
        },
        {
            "aid": 956311218,
            "bvid": "BV1fp4y1V783",
            "title": "\u3010\u4e50\u6b63\u7eebAI\u3011\u300a\u4e0d\u8001\u4e0d\u6b7b\u300b\u3010Ace Studio Cover\u3011",
            "pubdate": 1690194324,
            "author": "\u4e00\u6c5f\u6d41\u624d\u5c3d",
            "mid": 345719913,
            "view": 705,
            "danmaku": 0,
            "reply": 17,
            "favorite": 20,
            "coin": 5,
            "share": 2,
            "like": 34,
            "score": 871,
            "index": 40,
            "pickup": 0,
            "pic": "http://i0.hdslb.com/bfs/archive/0388c0200496465f2f8d25bcc9461e302c48cd27.jpg",
            "pubdate_str": "2023-07-24 18:25:24",
            "pic_url": "/cover/9/av956311218.jpg",
            "url": "https://www.bilibili.com/video/BV1fp4y1V783"
        }
    ],
    "pk": [
        {
            "aid": 998976921,
            "bvid": "BV1Lx4y1R7iF",
            "title": "\u3010\u6d1b\u5929\u4f9d/\u4e50\u6b63\u7eeb\u539f\u521b\u3011\u300a\u9177\u9177\u7684\u6211\uff0c\u5531\u7740\u9177\u9177\u7684\u6b4c\u300b",
            "pubdate": 1690371000,
            "author": "\u82b1\u56edGARDEN_",
            "mid": 3493277892348060,
            "view": 506,
            "danmaku": 1,
            "reply": 19,
            "favorite": 52,
            "coin": 22,
            "share": 5,
            "like": 103,
            "score": 2563,
            "index": 24,
            "pickup": 1,
            "pic": "http://i2.hdslb.com/bfs/archive/59c68cbb0619f129b424fe26f2051780848bd0df.jpg",
            "pubdate_str": "2023-07-26 19:30:00",
            "pic_url": "/cover/9/av998976921.jpg",
            "url": "https://www.bilibili.com/video/BV1Lx4y1R7iF"
        }
    ]
}